{
  "last_updated": "2025-10-21T08:33:57.928816",
  "latest_scrape": {
    "date": "2025-10-21",
    "total_headlines": 685,
    "sources_scraped": [
      "Bloomberg (Market News)",
      "Bloomberg (Economics)",
      "Bloomberg (Technology)",
      "Bloomberg (Business)",
      "Bloomberg (Opinion)",
      "Bloomberg (Wealth)",
      "CNBC (Economy)",
      "CNBC (Finance)",
      "CNBC (Business News)",
      "CNBC (Wealth)",
      "CNBC (Top News)",
      "CNBC (Earnings)",
      "CNBC (US News)",
      "CNBC (World News)",
      "CNBC (Retail)",
      "Wall Street Journal (Economy)",
      "Wall Street Journal (US Business)",
      "Wall Street Journal (Markets)",
      "Wall Street Journal (Politics)",
      "Wall Street Journal (Health)",
      "Wall Street Journal (Real Estate)",
      "Wall Street Journal (Personal Finance)",
      "Wall Street Journal (US News)",
      "Wall Street Journal (World News)",
      "Wall Street Journal (Tech)",
      "Yahoo News (Latest)",
      "Yahoo News (Finance)",
      "CBS (Top News)",
      "CBS (US News)",
      "CBS (World News)",
      "CBS (MoneyWatch)",
      "CBS (Health)",
      "CBS (Technology)",
      "CBS (Politics)",
      "ABC (Top Stories)",
      "ABC (US News)",
      "ABC (International News)",
      "ABC (Politics)",
      "ABC (Business)",
      "ABC (Technology)",
      "ABC (Health)",
      "New York Times (US)",
      "New York Times (World)",
      "New York Times (Politics)",
      "New York Times (Business)",
      "New York Times (Energy & Environment)",
      "New York Times (Economy)",
      "New York Times (Technology)",
      "New York Times (Health)",
      "Fox News (Latest)",
      "Fox News (U.S.)",
      "Fox News (World)",
      "Fox News (Politics)",
      "Fox News (Health)",
      "Fox News (Technology)",
      "Fox News (Opinion)",
      "Fox Business (Latest)",
      "Fox Business (Economy)",
      "Fox Business (Lifestyle)",
      "Fox Business (Videos)"
    ],
    "sources_organized": [
      "ABC (Business, Health, International News, Politics, Technology, Top Stories, US News)",
      "Bloomberg (Business, Economics, Market News, Opinion, Technology, Wealth)",
      "CBS (Health, MoneyWatch, Politics, Technology, Top News, US News, World News)",
      "CNBC (Business News, Earnings, Economy, Finance, Retail, Top News, US News, Wealth, World News)",
      "Fox Business (Economy, Latest, Lifestyle, Videos)",
      "Fox News (Health, Latest, Opinion, Politics, Technology, U.S., World)",
      "New York Times (Business, Economy, Energy & Environment, Health, Politics, Technology, US, World)",
      "Wall Street Journal (Economy, Health, Markets, Personal Finance, Politics, Real Estate, Tech, US Business, US News, World News)",
      "Yahoo News (Finance, Latest)"
    ],
    "relevance_score": 0.304,
    "sample_headlines": [
      {
        "title": "Philip Morris Lifts Outlook as Quarterly Profit, Revenue Rise",
        "source": "Wall Street Journal (US Business)",
        "link": "https://www.wsj.com/business/retail/philip-morris-lifts-outlook-as-quarterly-profit-revenue-rise-c17167f1?mod=pls_whats_news_us_business_f",
        "published_at": "2025-10-21T11:44:00Z"
      },
      {
        "title": "Kudlow: If Trump were king, we'd have a continuing resolution funding the government right now",
        "source": "Fox Business (Videos)",
        "link": "https://www.foxbusiness.com/video/6383427297112",
        "published_at": "2025-10-20T21:51:55Z"
      },
      {
        "title": "U.S., Australia Deal Advances Critical Minerals Ambitions, While Detail Light",
        "source": "Wall Street Journal (Economy)",
        "link": "https://www.wsj.com/economy/trade/u-s-australia-deal-advances-critical-minerals-ambitions-while-detail-light-d731e823",
        "published_at": "2025-10-21T10:01:00Z"
      },
      {
        "title": "With SpaceX Behind Schedule, NASA Will Seek More Moon Lander Ideas",
        "source": "New York Times (Politics)",
        "link": "https://www.nytimes.com/2025/10/20/science/nasa-moon-lander-spacex.html",
        "published_at": "2025-10-21T00:58:45Z"
      },
      {
        "title": "Business-Sales Outlook Weakens to Two-Year Low, Bank of Canada Survey Says",
        "source": "Wall Street Journal (World News)",
        "link": "https://www.wsj.com/world/americas/business-sales-outlook-weakens-to-two-year-low-bank-of-canada-survey-says-a428606e",
        "published_at": "2025-10-20T15:47:00Z"
      }
    ]
  },
  "total_days": 42,
  "total_headlines_collected": 24000,
  "date_range": {
    "start": "2025-09-10",
    "end": "2025-10-21"
  },
  "categories": {
    "macroeconomics": {
      "latest": 30,
      "average": 32.04761904761905,
      "total": 1346
    },
    "household": {
      "latest": 25,
      "average": 23.071428571428573,
      "total": 969
    },
    "trade": {
      "latest": 38,
      "average": 30.404761904761905,
      "total": 1277
    },
    "corporate_earnings": {
      "latest": 81,
      "average": 19.928571428571427,
      "total": 837
    },
    "fiscal_policy": {
      "latest": 5,
      "average": 4.785714285714286,
      "total": 201
    },
    "monetary_policy": {
      "latest": 7,
      "average": 11.952380952380953,
      "total": 502
    },
    "health_care": {
      "latest": 6,
      "average": 4.0476190476190474,
      "total": 170
    },
    "national_security": {
      "latest": 7,
      "average": 10.0,
      "total": 420
    },
    "regulation": {
      "latest": 4,
      "average": 4.023809523809524,
      "total": 169
    },
    "sovereign_debt_currency_crisis": {
      "latest": 0,
      "average": 0.023809523809523808,
      "total": 1
    },
    "entitlement_programs": {
      "latest": 1,
      "average": 2.357142857142857,
      "total": 99
    },
    "policy": {
      "latest": 4,
      "average": 9.023809523809524,
      "total": 379
    }
  }
}